{
  "ticker": "GWW",
  "company": "W.W. GRAINGER, INC.",
  "currency": "USD",
  "units": "MLN",
  "years": [
    {
      "col": 5,
      "fy": "FY 2007",
      "end_date": "12/31/2007"
    },
    {
      "col": 6,
      "fy": "FY 2008",
      "end_date": "12/31/2008"
    },
    {
      "col": 7,
      "fy": "FY 2009",
      "end_date": "12/31/2009"
    },
    {
      "col": 8,
      "fy": "FY 2010",
      "end_date": "12/31/2010"
    },
    {
      "col": 9,
      "fy": "FY 2011",
      "end_date": "12/31/2011"
    },
    {
      "col": 10,
      "fy": "FY 2012",
      "end_date": "12/31/2012"
    },
    {
      "col": 11,
      "fy": "FY 2013",
      "end_date": "12/31/2013"
    },
    {
      "col": 12,
      "fy": "FY 2014",
      "end_date": "12/31/2014"
    },
    {
      "col": 13,
      "fy": "FY 2015",
      "end_date": "12/31/2015"
    },
    {
      "col": 14,
      "fy": "FY 2016",
      "end_date": "12/31/2016"
    },
    {
      "col": 15,
      "fy": "FY 2017",
      "end_date": "12/31/2017"
    },
    {
      "col": 16,
      "fy": "FY 2018",
      "end_date": "12/31/2018"
    },
    {
      "col": 17,
      "fy": "FY 2019",
      "end_date": "12/31/2019"
    },
    {
      "col": 18,
      "fy": "FY 2020",
      "end_date": "12/31/2020"
    },
    {
      "col": 19,
      "fy": "FY 2021",
      "end_date": "12/31/2021"
    },
    {
      "col": 20,
      "fy": "FY 2022",
      "end_date": "12/31/2022"
    },
    {
      "col": 21,
      "fy": "FY 2023",
      "end_date": "12/31/2023"
    },
    {
      "col": 22,
      "fy": "FY 2024",
      "end_date": "12/31/2024"
    },
    {
      "col": 23,
      "fy": "FY 2025",
      "end_date": "12/31/2025"
    }
  ],
  "grid": {
    "14": {
      "label": "Revenue",
      "values": {
        "5": 6418.014,
        "6": 6850.032,
        "7": 6221.991,
        "8": 7182.158,
        "9": 8078.185,
        "10": 8950.045,
        "11": 9437.758,
        "12": 9964.953,
        "13": 9973.384,
        "14": 10137.0,
        "15": 10425.0,
        "16": 11221.0,
        "17": 11486.0,
        "18": 11797.0,
        "19": 13022.0,
        "20": 15228.0,
        "21": 16478.0,
        "22": 17168.0,
        "23": 17942.0
      }
    },
    "16": {
      "label": "Cost of Revenue",
      "values": {
        "5": 3814.391,
        "6": 4041.81,
        "7": 3623.465,
        "8": 4176.474,
        "9": 4567.393,
        "10": 5033.885,
        "11": 5301.275,
        "12": 5650.711,
        "13": 5741.956,
        "14": 6022.0,
        "15": 6327.0,
        "16": 6873.0,
        "17": 7089.0,
        "18": 7559.0,
        "19": 8302.0,
        "20": 9379.0,
        "21": 9982.0,
        "22": 10410.0,
        "23": 10933.0
      }
    },
    "18": {
      "label": "Gross Profit",
      "values": {
        "5": 2603.623,
        "6": 2808.222,
        "7": 2598.526,
        "8": 3005.684,
        "9": 3510.792,
        "10": 3916.16,
        "11": 4136.483,
        "12": 4314.242,
        "13": 4231.428,
        "14": 4115.0,
        "15": 4098.0,
        "16": 4348.0,
        "17": 4397.0,
        "18": 4238.0,
        "19": 4720.0,
        "20": 5849.0,
        "21": 6496.0,
        "22": 6758.0,
        "23": 7009.0
      }
    },
    "26": {
      "label": "Operating Income (Loss)",
      "values": {
        "5": 670.653,
        "6": 782.672,
        "7": 665.224,
        "8": 860.475,
        "9": 1052.429,
        "10": 1131.125,
        "11": 1296.854,
        "12": 1347.117,
        "13": 1300.32,
        "14": 1113.0,
        "15": 1035.0,
        "16": 1158.0,
        "17": 1262.0,
        "18": 1019.0,
        "19": 1547.0,
        "20": 2215.0,
        "21": 2565.0,
        "22": 2637.0,
        "23": 2495.0
      }
    },
    "27": {
      "label": "Non-Operating (Income) Loss",
      "values": {
        "5": 11.208,
        "6": -9.454,
        "7": 42.113,
        "8": -6.697,
        "9": -0.902,
        "10": -13.336,
        "11": -9.255,
        "12": -12.731,
        "13": -49.615,
        "14": -94.0,
        "15": -99.0,
        "16": -77.0,
        "17": -53.0,
        "18": -72.0,
        "19": -62.0,
        "20": -69.0,
        "21": -65.0,
        "22": -53.0,
        "23": -65.0
      }
    },
    "28": {
      "label": "Interest Expense",
      "values": {
        "5": 2.974,
        "6": 14.485,
        "7": 8.766,
        "8": 8.187,
        "9": 9.091,
        "10": 16.078,
        "11": 13.225,
        "12": 10.093,
        "13": 33.571,
        "14": 76.0,
        "15": 89.0,
        "16": 88.0
      }
    },
    "50": {
      "label": "Income (Loss) Incl. MI",
      "values": {
        "5": 420.12,
        "6": 475.355,
        "7": 430.466,
        "8": 510.865,
        "9": 658.423,
        "10": 689.881,
        "11": 797.036,
        "12": 801.729,
        "13": 768.996,
        "14": 606.0,
        "15": 586.0,
        "16": 782.0,
        "17": 849.0,
        "18": 695.0,
        "19": 1043.0,
        "20": 1547.0,
        "21": 1829.0,
        "22": 1909.0,
        "23": 1706.0
      }
    },
    "62": {
      "label": "Basic EPS, GAAP",
      "values": {
        "5": 5.01,
        "6": 6.07,
        "7": 5.7,
        "8": 7.05,
        "9": 9.26,
        "10": 9.71,
        "11": 11.31,
        "12": 11.59,
        "13": 11.69,
        "14": 9.94,
        "15": 10.07,
        "16": 13.82,
        "17": 15.39,
        "18": 12.88,
        "19": 19.94,
        "20": 30.22,
        "21": 36.39,
        "22": 38.84,
        "23": 35.47
      }
    },
    "99": {
      "label": "Cash & Cash Equivalents",
      "values": {
        "5": 113.437,
        "6": 396.29,
        "7": 459.871,
        "8": 313.454,
        "9": 335.491,
        "10": 452.063,
        "11": 430.644,
        "12": 226.644,
        "13": 290.136,
        "14": 274.0,
        "15": 327.0,
        "16": 538.0,
        "17": 360.0,
        "18": 585.0,
        "19": 241.0,
        "20": 325.0,
        "21": 660.0,
        "22": 1036.0,
        "23": 585.0
      }
    },
    "121": {
      "label": "Goodwill",
      "values": {
        "5": 233.028,
        "6": 213.159,
        "7": 351.182,
        "8": 387.232,
        "9": 509.183,
        "10": 543.67,
        "11": 525.467,
        "12": 506.905,
        "13": 582.336,
        "14": 527.15,
        "15": 544.0,
        "16": 424.0,
        "17": 429.0,
        "18": 391.0,
        "19": 384.0,
        "20": 371.0,
        "21": 370.0,
        "22": 355.0,
        "23": 360.0
      }
    },
    "177": {
      "label": "Shares Outstanding",
      "values": {
        "5": 82.403958,
        "6": 76.579856,
        "7": 73.786346,
        "8": 70.836945,
        "9": 69.690854,
        "10": 69.811881,
        "11": 69.455507,
        "12": 68.334322,
        "13": 65.156864,
        "14": 60.430892,
        "15": 57.7,
        "16": 56.1,
        "17": 54.7,
        "18": 53.5,
        "19": 51.9,
        "20": 50.9,
        "21": 49.9,
        "22": 48.9,
        "23": 47.9
      }
    },
    "209": {
      "label": "Cash from Operating Activities",
      "values": {
        "5": 468.875,
        "6": 530.066,
        "7": 732.396,
        "8": 596.445,
        "9": 746.108,
        "10": 816.195,
        "11": 986.498,
        "12": 959.814,
        "13": 1036.109,
        "14": 1024.0,
        "15": 1057.0,
        "16": 1057.0,
        "17": 1042.0,
        "18": 1123.0,
        "19": 937.0,
        "20": 1333.0,
        "21": 2031.0,
        "22": 2111.0,
        "23": 2015.0
      }
    },
    "212": {
      "label": "Change in Fixed & Intang",
      "values": {
        "5": -197.423,
        "6": -194.975,
        "7": -142.414,
        "8": -127.124,
        "9": -196.942,
        "10": -249.86,
        "11": -272.145,
        "12": -387.39,
        "13": -373.868,
        "14": -284.0,
        "15": -237.0,
        "16": -239.0,
        "17": -221.0,
        "18": -197.0,
        "19": -255.0,
        "20": -256.0,
        "21": -445.0,
        "22": -541.0,
        "23": -684.0
      }
    },
    "222": {
      "label": "Net Cash From Acq & Div",
      "values": {
        "5": -9.48,
        "6": -34.29,
        "7": -123.093,
        "8": -62.072,
        "9": -359.296,
        "10": -64.808,
        "11": -153.915,
        "12": -30.713,
        "13": -464.431,
        "14": -0.159,
        "15": -0.0
      }
    },
    "113": {
      "label": "Total Current Assets",
      "values": {
        "6": 2144.109,
        "7": 2131.515,
        "8": 2238.071,
        "9": 2694.9,
        "10": 2900.64,
        "11": 3044.285,
        "12": 2967.549,
        "13": 3048.642,
        "14": 3020.229,
        "15": 3205.989,
        "16": 3557.0,
        "17": 3555.0,
        "18": 3919.0,
        "19": 4011.0,
        "20": 4977.0,
        "21": 5274.0,
        "22": 5737.0,
        "23": 5484.0
      }
    },
    "114": {
      "label": "Property, Plant & Equip, Net",
      "values": {
        "6": 930.311,
        "7": 953.271,
        "8": 963.672,
        "9": 1060.295,
        "10": 1144.573,
        "11": 1208.562,
        "12": 1324.346,
        "13": 1431.241,
        "14": 1420.891,
        "15": 1391.967,
        "16": 1352.0,
        "17": 1400.0,
        "18": 1395.0,
        "19": 1424.0,
        "20": 1461.0,
        "21": 1658.0,
        "22": 1927.0,
        "23": 2268.0
      }
    },
    "128": {
      "label": "Total Assets",
      "values": {
        "6": 3515.417,
        "7": 3726.332,
        "8": 3904.377,
        "9": 4716.062,
        "10": 5014.598,
        "11": 5266.328,
        "12": 5283.049,
        "13": 5857.755,
        "14": 5694.307,
        "15": 5804.0,
        "16": 5873.0,
        "17": 6005.0,
        "18": 6295.0,
        "19": 6592.0,
        "20": 7588.0,
        "21": 8147.0,
        "22": 8829.0,
        "23": 8962.0
      }
    },
    "136": {
      "label": "ST Debt",
      "values": {
        "6": 19.96,
        "7": 34.78,
        "8": 42.769,
        "9": 119.97,
        "10": 79.071,
        "11": 66.857,
        "12": 56.896,
        "13": 353.072,
        "14": 386.14,
        "15": 55.603,
        "16": 49.0,
        "17": 55.0,
        "18": 8.0,
        "19": 0.0,
        "20": 35.0,
        "21": 34.0,
        "22": 499.0,
        "23": 126.0
      }
    },
    "146": {
      "label": "Total Current Liabilities",
      "values": {
        "6": 761.734,
        "7": 776.799,
        "8": 869.303,
        "9": 1387.925,
        "10": 1080.003,
        "11": 1195.79,
        "12": 1261.716,
        "13": 1788.534,
        "14": 1628.937,
        "15": 1506.661,
        "16": 1501.0,
        "17": 1678.0,
        "18": 1441.0,
        "19": 1528.0,
        "20": 2010.0,
        "21": 1831.0,
        "22": 2305.0,
        "23": 1940.0
      }
    },
    "147": {
      "label": "LT Debt",
      "values": {
        "6": 488.228,
        "7": 437.5,
        "8": 420.446,
        "9": 175.055,
        "10": 467.048,
        "11": 445.513,
        "12": 404.536,
        "13": 1388.414,
        "14": 1840.946,
        "15": 2248.036,
        "16": 2090.0,
        "17": 1914.0,
        "18": 2389.0,
        "19": 2362.0,
        "20": 2284.0,
        "21": 2266.0,
        "22": 2279.0,
        "23": 2362.0
      }
    },
    "164": {
      "label": "Share Capital & APIC",
      "values": {
        "6": 54.83,
        "7": 54.83,
        "8": 54.83,
        "9": 54.83,
        "10": 54.83,
        "11": 54.83,
        "12": 54.83,
        "13": 54.83,
        "14": 54.83,
        "15": 54.83,
        "16": 55.0,
        "17": 55.0,
        "18": 55.0,
        "19": 55.0,
        "20": 55.0,
        "21": 55.0,
        "22": 55.0,
        "23": 55.0
      }
    },
    "167": {
      "label": "Treasury Stock",
      "values": {
        "6": 2217.954,
        "7": 2466.35,
        "8": 2857.012,
        "9": 2904.243,
        "10": 3175.646,
        "11": 3548.973,
        "12": 4032.615,
        "13": 5369.711,
        "14": 6128.416,
        "15": 6675.709,
        "16": 6966.0,
        "17": 7633.0,
        "18": 8184.0,
        "19": 8855.0,
        "20": 9445.0
      }
    },
    "168": {
      "label": "Retained Earnings",
      "values": {
        "6": 3670.726,
        "7": 3966.508,
        "8": 4326.761,
        "9": 4806.11,
        "10": 5278.577,
        "11": 5822.612,
        "12": 6335.99,
        "13": 6802.13,
        "14": 7113.559,
        "15": 7405.192,
        "16": 7869.0,
        "17": 8405.0,
        "18": 8779.0,
        "19": 9500.0,
        "20": 10700.0,
        "21": 12162.0,
        "22": 13677.0,
        "23": 14958.0
      }
    },
    "172": {
      "label": "Total Equity",
      "values": {
        "6": 2033.805,
        "7": 2163.72,
        "8": 2205.216,
        "9": 2628.785,
        "10": 3023.912,
        "11": 3250.438,
        "12": 3209.872,
        "13": 2266.634,
        "14": 1797.935,
        "15": 1690.132,
        "16": 1921.0,
        "17": 1855.0,
        "18": 1828.0,
        "19": 1874.0,
        "20": 2440.0,
        "21": 3115.0,
        "22": 3358.0,
        "23": 3736.0
      }
    },
    "11": {
      "label": "Effective tax rate",
      "values": {
        "21": 25.596707818930042
      }
    }
  },
  "source": "edgar",
  "source_provider": "SEC EDGAR XBRL",
  "source_fetched_at": "2026-06-12T15:13:20Z"
}