{
  "ticker": "O",
  "company": "REALTY INCOME CORP",
  "currency": "USD",
  "units": "MLN",
  "years": [
    {
      "col": 5,
      "fy": "FY 2008",
      "end_date": "12/31/2008"
    },
    {
      "col": 6,
      "fy": "FY 2009",
      "end_date": "12/31/2009"
    },
    {
      "col": 7,
      "fy": "FY 2010",
      "end_date": "12/31/2010"
    },
    {
      "col": 8,
      "fy": "FY 2011",
      "end_date": "12/31/2011"
    },
    {
      "col": 9,
      "fy": "FY 2016",
      "end_date": "12/31/2016"
    },
    {
      "col": 10,
      "fy": "FY 2017",
      "end_date": "12/31/2017"
    },
    {
      "col": 11,
      "fy": "FY 2018",
      "end_date": "12/31/2018"
    },
    {
      "col": 12,
      "fy": "FY 2019",
      "end_date": "12/31/2019"
    },
    {
      "col": 13,
      "fy": "FY 2020",
      "end_date": "12/31/2020"
    },
    {
      "col": 14,
      "fy": "FY 2021",
      "end_date": "12/31/2021"
    },
    {
      "col": 15,
      "fy": "FY 2022",
      "end_date": "12/31/2022"
    },
    {
      "col": 16,
      "fy": "FY 2023",
      "end_date": "12/31/2023"
    },
    {
      "col": 17,
      "fy": "FY 2024",
      "end_date": "12/31/2024"
    },
    {
      "col": 18,
      "fy": "FY 2025",
      "end_date": "12/31/2025"
    }
  ],
  "grid": {
    "14": {
      "label": "Revenue",
      "values": {
        "5": 325.041,
        "6": 322.55,
        "7": 343.492,
        "8": 421.059,
        "9": 1103.172,
        "10": 1215.768,
        "11": 1327.838,
        "12": 1488.163,
        "13": 1647.087,
        "14": 2080.463,
        "15": 3343.681,
        "16": 4078.993,
        "17": 5271.142,
        "18": 5749.377
      }
    },
    "28": {
      "label": "Interest Expense",
      "values": {
        "5": 93.956,
        "6": 85.528,
        "7": 93.237,
        "8": 108.301,
        "9": 219.974,
        "10": 247.413,
        "11": 266.02,
        "12": 290.991,
        "13": 309.336,
        "14": 323.644,
        "15": 465.223,
        "16": 730.423
      }
    },
    "50": {
      "label": "Income (Loss) Incl. MI",
      "values": {
        "5": 131.841,
        "6": 131.127,
        "7": 130.784,
        "8": 157.032,
        "9": 315.571,
        "10": 318.798,
        "11": 363.614,
        "12": 436.482,
        "13": 395.486,
        "14": 359.456,
        "15": 869.408,
        "16": 872.309,
        "17": 860.772,
        "18": 1058.59
      }
    },
    "172": {
      "label": "Total Equity",
      "values": {
        "5": 1554.661,
        "6": 1488.009,
        "7": 1846.965,
        "8": 2254.854,
        "9": 6766.804,
        "10": 7371.501,
        "11": 8088.742,
        "12": 9774.456,
        "13": 10985.483,
        "14": 25052.574,
        "15": 28713.149,
        "16": 32941.467,
        "17": 38840.738,
        "18": 39438.695
      }
    },
    "177": {
      "label": "Shares Outstanding",
      "values": {
        "5": 101.178191,
        "6": 103.577507,
        "7": 105.869637,
        "8": 126.142696,
        "9": 255.0665,
        "10": 273.46568,
        "11": 289.42743,
        "12": 315.837012,
        "13": 345.280126,
        "14": 414.535,
        "15": 611.766,
        "16": 692.298,
        "17": 862.959,
        "18": 907.169
      }
    },
    "209": {
      "label": "Cash from Operating Activities",
      "values": {
        "5": 246.155,
        "6": 226.707,
        "7": 243.368,
        "8": 298.952,
        "9": 799.863,
        "10": 875.85,
        "11": 940.742,
        "12": 1068.937,
        "13": 1115.543,
        "14": 1322.189,
        "15": 2563.856,
        "16": 2958.769,
        "17": 3573.276,
        "18": 3994.754
      }
    },
    "62": {
      "label": "Basic EPS, GAAP",
      "values": {
        "7": 1.01,
        "8": 1.05,
        "11": 1.26,
        "12": 1.38,
        "13": 1.15,
        "14": 0.87,
        "15": 1.42,
        "16": 1.26,
        "17": 0.98,
        "18": 1.17
      }
    },
    "121": {
      "label": "Goodwill",
      "values": {
        "7": 17.206,
        "8": 17.206,
        "9": 15.067,
        "10": 14.97,
        "11": 14.63,
        "12": 14.43,
        "13": 14.18,
        "14": 3676.705,
        "15": 3731.478,
        "16": 3731.478,
        "17": 4932.199,
        "18": 4932.199
      }
    },
    "128": {
      "label": "Total Assets",
      "values": {
        "7": 3535.59,
        "8": 4419.389,
        "9": 13152.871,
        "10": 14058.166,
        "11": 15260.483,
        "12": 18554.796,
        "13": 20740.285,
        "14": 43137.502,
        "15": 49673.092,
        "16": 57779.357,
        "17": 68835.039,
        "18": 72795.612
      }
    },
    "147": {
      "label": "LT Debt",
      "values": {
        "8": 1750.0
      }
    },
    "164": {
      "label": "Share Capital & APIC",
      "values": {
        "9": 8228.594,
        "10": 9624.264,
        "11": 10754.495,
        "12": 12873.849,
        "13": 14700.05,
        "14": 29578.212,
        "15": 34159.509,
        "16": 39629.709,
        "17": 47451.068,
        "18": 49861.66
      }
    },
    "99": {
      "label": "Cash & Cash Equivalents",
      "values": {
        "10": 6.898,
        "11": 10.387,
        "12": 54.011,
        "13": 824.476,
        "14": 258.579,
        "15": 171.102,
        "16": 232.923,
        "17": 444.962,
        "18": 434.842
      }
    },
    "20": {
      "label": "Operating Expenses",
      "values": {
        "12": 1080.206,
        "13": 1311.424,
        "14": 1658.444,
        "15": 2540.158,
        "16": 3188.646,
        "17": 4489.294,
        "18": 4785.982
      }
    },
    "27": {
      "label": "Non-Operating (Income) Loss",
      "values": {
        "12": 3.428,
        "13": 4.538,
        "14": 9.949,
        "15": 30.511,
        "16": 23.789,
        "17": 23.606,
        "18": 29.417
      }
    },
    "222": {
      "label": "Net Cash From Acq & Div",
      "values": {
        "12": -0.0,
        "13": -0.0,
        "14": -366.03,
        "15": -0.0,
        "16": -0.0
      }
    },
    "11": {
      "label": "Effective tax rate",
      "values": {
        "21": 7.3884388670010015
      }
    }
  },
  "source": "edgar",
  "source_provider": "SEC EDGAR XBRL",
  "source_fetched_at": "2026-06-12T15:15:39Z"
}