{
  "ticker": "VRTX",
  "company": "VERTEX PHARMACEUTICALS INC / MA",
  "currency": "USD",
  "units": "MLN",
  "years": [
    {
      "col": 5,
      "fy": "FY 2008",
      "end_date": "12/31/2008"
    },
    {
      "col": 6,
      "fy": "FY 2009",
      "end_date": "12/31/2009"
    },
    {
      "col": 7,
      "fy": "FY 2010",
      "end_date": "12/31/2010"
    },
    {
      "col": 8,
      "fy": "FY 2011",
      "end_date": "12/31/2011"
    },
    {
      "col": 9,
      "fy": "FY 2012",
      "end_date": "12/31/2012"
    },
    {
      "col": 10,
      "fy": "FY 2013",
      "end_date": "12/31/2013"
    },
    {
      "col": 11,
      "fy": "FY 2014",
      "end_date": "12/31/2014"
    },
    {
      "col": 12,
      "fy": "FY 2015",
      "end_date": "12/31/2015"
    },
    {
      "col": 13,
      "fy": "FY 2016",
      "end_date": "12/31/2016"
    },
    {
      "col": 14,
      "fy": "FY 2017",
      "end_date": "12/31/2017"
    },
    {
      "col": 15,
      "fy": "FY 2018",
      "end_date": "12/31/2018"
    },
    {
      "col": 16,
      "fy": "FY 2019",
      "end_date": "12/31/2019"
    },
    {
      "col": 17,
      "fy": "FY 2020",
      "end_date": "12/31/2020"
    },
    {
      "col": 18,
      "fy": "FY 2021",
      "end_date": "12/31/2021"
    },
    {
      "col": 19,
      "fy": "FY 2022",
      "end_date": "12/31/2022"
    },
    {
      "col": 20,
      "fy": "FY 2023",
      "end_date": "12/31/2023"
    },
    {
      "col": 21,
      "fy": "FY 2024",
      "end_date": "12/31/2024"
    },
    {
      "col": 22,
      "fy": "FY 2025",
      "end_date": "12/31/2025"
    }
  ],
  "grid": {
    "14": {
      "label": "Revenue",
      "values": {
        "5": 175.504,
        "6": 101.889,
        "7": 143.37,
        "8": 1410.626,
        "9": 1527.042,
        "10": 1211.975,
        "11": 580.415,
        "12": 1032.336,
        "13": 1702.177,
        "14": 2488.652,
        "15": 3047.597,
        "16": 4162.8,
        "17": 6205.7,
        "18": 7574.4,
        "19": 8930.7,
        "20": 9869.2,
        "21": 11020.1,
        "22": 12001.3
      }
    },
    "20": {
      "label": "Operating Expenses",
      "values": {
        "5": 638.212,
        "6": 715.901,
        "7": 839.447,
        "8": 1296.806,
        "9": 1480.315,
        "10": 1821.983,
        "11": 1272.827,
        "12": 1499.215,
        "13": 1692.241,
        "14": 2365.409,
        "15": 2412.447,
        "16": 2965.3,
        "17": 3349.4,
        "18": 4792.3,
        "19": 4623.3,
        "20": 6037.2,
        "21": 11253.0,
        "22": 7828.0
      }
    },
    "26": {
      "label": "Operating Income (Loss)",
      "values": {
        "5": -462.708,
        "6": -614.012,
        "7": -696.077,
        "8": 113.82,
        "9": 46.727,
        "10": -610.008,
        "11": -692.412,
        "12": -466.879,
        "13": 9.936,
        "14": 123.243,
        "15": 635.15,
        "16": 1197.5,
        "17": 2856.3,
        "18": 2782.1,
        "19": 4307.4,
        "20": 3832.0,
        "21": -232.9,
        "22": 4173.3
      }
    },
    "28": {
      "label": "Interest Expense",
      "values": {
        "5": 13.471,
        "6": 13.192,
        "7": 19.275,
        "8": 38.452,
        "9": 16.653,
        "14": 69.298,
        "15": 72.471,
        "16": 58.502,
        "17": 58.151
      }
    },
    "62": {
      "label": "Basic EPS, GAAP",
      "values": {
        "5": -3.27,
        "6": -3.71,
        "7": -3.77,
        "8": 0.14,
        "9": -0.5,
        "10": -1.98,
        "11": -3.14,
        "12": -2.31,
        "13": -0.46,
        "14": 1.06,
        "15": 8.24,
        "16": 4.58,
        "17": 10.44,
        "18": 9.09,
        "19": 12.97,
        "20": 14.05,
        "21": -2.08,
        "22": 15.46
      }
    },
    "99": {
      "label": "Cash & Cash Equivalents",
      "values": {
        "5": 389.115,
        "6": 446.658,
        "7": 243.197,
        "8": 475.32,
        "9": 489.407,
        "10": 569.299,
        "11": 625.259,
        "12": 714.768,
        "13": 1183.945,
        "14": 1665.412,
        "15": 2650.134,
        "16": 3109.3,
        "17": 5988.2,
        "18": 6795.0,
        "19": 10504.0,
        "20": 10369.1,
        "21": 4569.6,
        "22": 5084.8
      }
    },
    "172": {
      "label": "Total Equity",
      "values": {
        "5": 238.874,
        "6": 1096.346,
        "7": 503.973,
        "8": 786.843,
        "9": 999.18,
        "10": 1356.405,
        "11": 1075.006,
        "12": 939.967,
        "13": 1156.582,
        "14": 2028.579,
        "15": 4435.203,
        "16": 6085.2,
        "17": 8686.8,
        "18": 10100.0,
        "19": 13912.7,
        "20": 17580.4,
        "21": 16409.6,
        "22": 18665.8
      }
    },
    "177": {
      "label": "Shares Outstanding",
      "values": {
        "5": 140.556,
        "6": 173.259,
        "7": 200.402,
        "8": 204.891,
        "9": 211.946,
        "10": 224.906,
        "11": 235.307,
        "12": 241.312,
        "13": 244.685,
        "14": 248.858,
        "15": 254.292,
        "16": 256.7,
        "17": 259.8,
        "18": 257.7,
        "19": 256.1,
        "20": 257.7,
        "21": 257.9,
        "22": 255.7
      }
    },
    "209": {
      "label": "Cash from Operating Activities",
      "values": {
        "5": -226.482,
        "6": -427.586,
        "7": -635.442,
        "8": 143.735,
        "9": 267.841,
        "10": -60.666,
        "11": -573.112,
        "12": -365.432,
        "13": 236.103,
        "14": 844.942,
        "15": 1270.286,
        "16": 1569.3,
        "17": 3253.5,
        "18": 2643.5,
        "19": 4129.9,
        "20": 3537.3,
        "21": -492.6,
        "22": 3631.4
      }
    },
    "212": {
      "label": "Change in Fixed & Intang",
      "values": {
        "5": -32.18,
        "6": -23.496,
        "7": -38.054,
        "8": -34.595,
        "9": -71.14,
        "10": -51.393,
        "11": -51.201,
        "12": -45.302,
        "13": -56.563,
        "14": -99.421,
        "15": -95.449,
        "16": -75.4,
        "17": -259.8,
        "18": -235.0,
        "19": -204.7,
        "20": -200.4,
        "21": -297.7,
        "22": -437.6
      }
    },
    "50": {
      "label": "Income (Loss) Incl. MI",
      "values": {
        "6": -642.178,
        "7": -754.626,
        "8": 29.574,
        "9": -107.032,
        "10": -445.028,
        "11": -738.555,
        "12": -556.334,
        "13": -112.052,
        "14": 263.484,
        "15": 2096.896,
        "16": 1176.8,
        "17": 2711.7,
        "18": 2342.1,
        "19": 3322.0,
        "20": 3619.6,
        "21": -535.6,
        "22": 3953.2
      }
    },
    "222": {
      "label": "Net Cash From Acq & Div",
      "values": {
        "6": -87.422,
        "14": -0.0,
        "15": -0.0,
        "16": -1154.2,
        "17": -0.0,
        "18": -0.0,
        "19": -295.9,
        "20": -0.0,
        "21": -0.0
      }
    },
    "113": {
      "label": "Total Current Assets",
      "values": {
        "7": 1057.039,
        "8": 1331.254,
        "9": 1589.585,
        "10": 1588.576,
        "11": 1546.511,
        "12": 1407.153,
        "13": 1831.54,
        "14": 2648.963,
        "15": 3843.109,
        "16": 4822.829,
        "17": 8133.379,
        "18": 9560.6,
        "19": 13234.8,
        "20": 14144.2,
        "21": 9596.4,
        "22": 11201.0
      }
    },
    "114": {
      "label": "Property, Plant & Equip, Net",
      "values": {
        "7": 72.333,
        "8": 133.176,
        "9": 433.609,
        "10": 696.911,
        "11": 715.812,
        "12": 697.715,
        "13": 698.362,
        "14": 789.437,
        "15": 812.005
      }
    },
    "121": {
      "label": "Goodwill",
      "values": {
        "7": 26.102,
        "8": 30.992,
        "9": 30.992,
        "10": 30.992,
        "11": 39.915,
        "12": 50.384,
        "13": 50.384,
        "14": 50.384,
        "15": 50.384,
        "16": 1002.158,
        "17": 1002.158,
        "18": 1002.2,
        "19": 1088.0,
        "20": 1088.0,
        "21": 1088.0,
        "22": 1088.0
      }
    },
    "128": {
      "label": "Total Assets",
      "values": {
        "7": 1725.446,
        "8": 2204.28,
        "9": 2759.288,
        "10": 2319.041,
        "11": 2334.679,
        "12": 2498.875,
        "13": 2896.787,
        "14": 3546.014,
        "15": 6245.898,
        "16": 8318.465,
        "17": 11751.808,
        "18": 13432.5,
        "19": 18150.9,
        "20": 22730.2,
        "21": 22533.2,
        "22": 25643.0
      }
    },
    "131": {
      "label": "Payables & Accruals",
      "values": {
        "7": 35.851,
        "8": 74.642,
        "9": 101.292,
        "10": 49.327,
        "11": 71.194,
        "12": 74.942,
        "13": 61.451,
        "14": 73.994,
        "15": 110.987,
        "16": 87.61,
        "17": 155.139,
        "18": 195.0,
        "19": 303.9,
        "20": 364.9,
        "21": 413.0,
        "22": 461.7
      }
    },
    "146": {
      "label": "Total Current Liabilities",
      "values": {
        "7": 474.783,
        "8": 392.348,
        "9": 432.624,
        "10": 397.829,
        "11": 368.254,
        "12": 506.349,
        "13": 792.537,
        "14": 807.26,
        "15": 1120.292,
        "16": 1334.827,
        "17": 1877.533,
        "18": 2142.0,
        "19": 2742.1,
        "20": 3547.4,
        "21": 3564.6,
        "22": 3861.2
      }
    },
    "164": {
      "label": "Share Capital & APIC",
      "values": {
        "7": 2.016,
        "8": 2.072,
        "9": 2.149,
        "10": 2.32,
        "11": 2.385,
        "12": 2.427,
        "13": 2.45,
        "14": 2.512,
        "15": 2.546,
        "16": 2.589,
        "17": 2.599,
        "18": 2.5,
        "19": 2.6,
        "20": 2.6,
        "21": 2.6,
        "22": 2.5
      }
    },
    "168": {
      "label": "Retained Earnings",
      "values": {
        "7": -3444.409,
        "8": -3414.835,
        "9": -3521.867,
        "10": -3966.895,
        "11": -4705.45,
        "12": -5261.784,
        "13": -5373.836,
        "14": -5119.723,
        "15": -2989.478,
        "16": -1852.978,
        "17": 858.669,
        "18": 3200.8,
        "19": 6522.8,
        "20": 10142.4,
        "21": 9606.8,
        "22": 13560.0
      }
    },
    "232": {
      "label": "Cash From (Repayment) Debt",
      "values": {
        "7": 0.0,
        "8": 155.0,
        "9": 0.0,
        "10": 0.158,
        "11": 0.0,
        "12": 0.0
      }
    },
    "27": {
      "label": "Non-Operating (Income) Loss",
      "values": {
        "8": -15.694,
        "9": 0.309,
        "10": 6.89,
        "11": 30.4,
        "12": -6.715,
        "13": 4.13,
        "14": -81.382,
        "15": -0.79,
        "16": 192.2,
        "17": 296.6,
        "18": 4.9,
        "19": -164.8,
        "20": -22.8,
        "21": -86.1,
        "22": -7.7
      }
    },
    "152": {
      "label": "Other LT Liabilities",
      "values": {
        "8": 7.287,
        "9": 13.902,
        "10": 11.59,
        "11": 21.707,
        "12": 31.778,
        "13": 102.122,
        "14": 26.048,
        "15": 26.28,
        "16": 183.318,
        "17": 108.355,
        "18": 116.8,
        "19": 685.8,
        "20": 877.7,
        "21": 901.8,
        "22": 1269.5
      }
    },
    "16": {
      "label": "Cost of Revenue",
      "values": {
        "13": 210.46,
        "14": 275.119,
        "15": 409.539,
        "16": 547.8,
        "17": 736.3,
        "18": 904.2,
        "19": 1080.3,
        "20": 1262.2,
        "21": 1530.5,
        "22": 1651.3
      }
    },
    "11": {
      "label": "Effective tax rate",
      "values": {
        "21": 14.860441075120606
      }
    }
  },
  "source": "edgar",
  "source_provider": "SEC EDGAR XBRL",
  "source_fetched_at": "2026-06-12T15:09:17Z"
}